compare_user_agent_strings/__init__.py
compare_user_agent_strings/__main__.py
compare_user_agent_strings/__version__.py
compare_user_agent_strings/run_examples.py
compare_user_agent_strings/ua_fingerprint.py
compare_user_agent_strings-1.0.2.dist-info/LICENSE
compare_user_agent_strings-1.0.2.dist-info/METADATA
compare_user_agent_strings-1.0.2.dist-info/WHEEL
compare_user_agent_strings-1.0.2.dist-info/top_level.txt
compare_user_agent_strings-1.0.2.dist-info/RECORD
