Metadata-Version: 2.1
Name: compare-user-agent-strings
Version: 1.0.2
Summary: Compares pair of user-agent strings to detect stolen authentication cookie.
Home-page: https://github.com/jimratliff/compare-user-agent-strings-python
Author: Jim Ratliff
Author-email: jim@jim-ratliff.name
Project-URL: Bug Tracker, https://github.com/jimratliff/compare-user-agent-strings-python/issues
Classifier: Programming Language :: Python :: 3.9
Classifier: License :: OSI Approved :: MIT License
Classifier: Operating System :: OS Independent
Classifier: Intended Audience :: Developers
Requires-Python: >=3.9
License-File: LICENSE
Requires-Dist: ua-parser
